kuv/__init__.py
kuv/ipynb_metadata.py
kuv/kernel_launcher.py
kuv-0.1.5.data/data/share/jupyter/kernels/kuv/kernel.json
kuv-0.1.5.data/data/share/jupyter/kernels/kuv/logo-32x32.png
kuv-0.1.5.data/data/share/jupyter/kernels/kuv/logo-64x64.png
kuv-0.1.5.data/data/share/jupyter/kernels/kuv/logo-svg.svg
kuv-0.1.5.dist-info/METADATA
kuv-0.1.5.dist-info/WHEEL
kuv-0.1.5.dist-info/licenses/LICENSE
kuv-0.1.5.dist-info/RECORD
